<?xml version="1.0" encoding="utf-8"?>
<Patch>
  <Operation Class="PatchOperationConditional">
    <xpath>/Defs/ThingDef[defName="Dhole"]</xpath>
    <success>Always</success>
    <match Class="PatchOperationAdd">
      <xpath>/Defs/Revolus.DogsMate.AnimalGroupDef[defName="Wolf"]/pawnKinds</xpath>
      <value>
        <li>Dhole</li>
        <li>Manedwolf</li>
      </value>
    </match>
  </Operation>
  <Operation Class="PatchOperationConditional">
    <xpath>/Defs/ThingDef[defName="Dingo"]</xpath>
    <success>Always</success>
    <match Class="PatchOperationAdd">
      <xpath>/Defs/Revolus.DogsMate.AnimalGroupDef[defName="Dog"]/pawnKinds</xpath>
      <value>
        <li>Dingo</li>
      </value>
    </match>
  </Operation>
  <Operation Class="PatchOperationConditional">
    <xpath>/Defs/ThingDef[defName="Racoon_dog"]</xpath>
    <success>Always</success>
    <match Class="PatchOperationAdd">
      <xpath>/Defs/Revolus.DogsMate.AnimalGroupDef[defName="Tanuki"]/pawnKinds</xpath>
      <value>
        <li>Racoon_dog</li>
      </value>
    </match>
  </Operation>
</Patch>